README.md
setup.py
totopubsub/__init__.py
totopubsub/logger.py
totopubsub/model.py
totopubsub/pubsub.py
totopubsub.egg-info/PKG-INFO
totopubsub.egg-info/SOURCES.txt
totopubsub.egg-info/dependency_links.txt
totopubsub.egg-info/requires.txt
totopubsub.egg-info/top_level.txt
totopubsub/impl/__init__.py
totopubsub/impl/aws/__init__.py
totopubsub/impl/aws/sns.py
totopubsub/impl/gcp/__init__.py
totopubsub/impl/gcp/gcppubsub.py