Metadata-Version: 2.1
Name: totopubsub
Version: 1.0.0
Summary: Agnostic PubSub implementation for Toto
Home-page: UNKNOWN
Author: nicolasances
Author-email: nicolas.matteazzi@gmail.com
License: UNKNOWN
Platform: UNKNOWN
